<?xml version="1.0" encoding="UTF-8" standalone="yes"?>


<item>
<title>[COLOR lime] DEADPOOL 2 [/COLOR]</title>
<urlsolve>http://streamcloud.eu/dcc9rxicymya</urlsolve>
<thumbnail><thumbnail>
<info></info> 
</item>


<item>
<title>[COLOR lime] Vengadores: La guerra del infinito [/COLOR]</title>
<urlsolve>http://streamcloud.eu/37zifeo9ubg7</urlsolve>
<thumbnail><thumbnail>
<info></info> 
</item>


<item>
<title>[COLOR lime] Operación: Huracán [/COLOR]</title>
<urlsolve>http://streamcloud.eu/0f7u0mx7dpf5</urlsolve>
<thumbnail><thumbnail>
<info></info> 
</item>


<item>
<title>[COLOR lime] Swinging Safari [/COLOR]</title>
<urlsolve>http://streamcloud.eu/m35om9w2k67v</urlsolve>
<thumbnail><thumbnail>
<info></info> 
</item>


<item>
<title>[COLOR lime] Ocean's 8: Las estafadoras [/COLOR]</title>
<urlsolve>http://streamcloud.eu/lf420tbfgvfr</urlsolve>
<thumbnail><thumbnail>
<info></info> 
</item>


<item>
<title>[COLOR lime] [/COLOR]</title>
<urlsolve></urlsolve>
<thumbnail><thumbnail>
<info></info> 
</item>

<item>
<title>[COLOR lime] [/COLOR]</title>
<urlsolve></urlsolve>
<thumbnail><thumbnail>
<info></info> 
</item>


<item>
<title>[COLOR lime] [/COLOR]</title>
<urlsolve></urlsolve>
<thumbnail><thumbnail>
<info></info> 
</item>


<item>
<title>[COLOR lime] [/COLOR]</title>
<urlsolve></urlsolve>
<thumbnail><thumbnail>
<info></info> 
</item>


<item>
<title>[COLOR lime] [/COLOR]</title>
<urlsolve></urlsolve>
<thumbnail><thumbnail>
<info></info> 
</item>


<item>
<title>[COLOR lime] [/COLOR]</title>
<urlsolve></urlsolve>
<thumbnail><thumbnail>
<info></info> 
</item>


<item>
<title>[COLOR lime] [/COLOR]</title>
<urlsolve></urlsolve>
<thumbnail><thumbnail>
<info></info> 
</item>
